ccstudiodss/__init__.py
ccstudiodss/__main__.py
ccstudiodss/_version.py
ccstudiodss/api.py
ccstudiodss/cli.py
ccstudiodss/pytest.py
ccstudiodss/utils.py
ccstudiodss-0.4.3.dist-info/METADATA
ccstudiodss-0.4.3.dist-info/WHEEL
ccstudiodss-0.4.3.dist-info/entry_points.txt
ccstudiodss-0.4.3.dist-info/top_level.txt
ccstudiodss-0.4.3.dist-info/RECORD
