Metadata-Version: 2.1
Name: ccstudiodss
Version: 0.4.3
Summary: Build and load Code Composer Studio projects from the command line using the Java DSS library.
Home-page: UNKNOWN
License: UNKNOWN
Platform: UNKNOWN
Classifier: Development Status :: 4 - Beta
Classifier: Intended Audience :: Developers
Classifier: Programming Language :: Python :: 3
Classifier: Programming Language :: Python :: 3.7
Requires-Dist: attrs
Requires-Dist: click
Requires-Dist: lxml
Provides-Extra: dev
Requires-Dist: gitignoreio ; extra == 'dev'
Provides-Extra: java
Requires-Dist: jpype1 (==1.*,>=1.1.2) ; extra == 'java'
Provides-Extra: test
Requires-Dist: pytest ; extra == 'test'
